{
    "mobile": {
        "headingH1FontWeight": 300,
        "headingH1FontSize": 28,
        "headingH1ParagraphSpacing": 32,
        "headingH1Indent": 0,
        "headingH1FontVariantNumeric": "String value",
        "headingH1FontFeatureSettings": "String value",
        "headingH1LineHeight": "120%",
        "headingH1LetterSpacing": "-0.5%",
        "headingH1FontBase": "Suisse Int'l",
        "headingH2FontBase": "Suisse Int'l",
        "headingH2FontWeight": 300,
        "headingH2FontSize": 24,
        "headingH2LineHeight": "120%",
        "headingH2LetterSpacing": "-0.5%",
        "headingH2ParagraphSpacing": 32,
        "headingH2Indent": 0,
        "headingH2FontVariantNumeric": "String value",
        "headingH2FontFeatureSettings": "String value",
        "headingH3FontBase": "Suisse Int'l",
        "headingH3FontWeight": 400,
        "headingH3FontSize": 20,
        "headingH3LineHeight": "120%",
        "headingH3LetterSpacing": "-0.5%",
        "headingH3ParagraphSpacing": 24,
        "headingH3Indent": 0,
        "headingH3FontVariantNumeric": "String value",
        "headingH3FontFeatureSettings": "String value",
        "headingH4FontBase": "Suisse Int'l",
        "headingH4FontWeight": 450,
        "headingH4FontSize": 18,
        "headingH4LineHeight": "120%",
        "headingH4LetterSpacing": "-0.5%",
        "headingH4ParagraphSpacing": 10,
        "headingH4Indent": 0,
        "headingH4FontVariantNumeric": "String value",
        "headingH4FontFeatureSettings": "String value",
        "leadFontBase": "Suisse Int'l",
        "leadFontWeight": 400,
        "leadFontSize": 24,
        "leadLineHeight": "120%",
        "leadLetterSpacing": "-0.5%",
        "leadParagraphSpacing": 10,
        "leadIndent": 32,
        "leadFontVariantNumeric": "String value",
        "leadFontFeatureSettings": "String value",
        "largeFontBase": "Suisse Int'l",
        "largeFontWeight": 400,
        "largeFontSize": 18,
        "largeLineHeight": "120%",
        "largeLetterSpacing": "-0.5%",
        "largeParagraphSpacing": 10,
        "largeIndent": 0,
        "largeFontVariantNumeric": "String value",
        "largeFontFeatureSettings": "String value",
        "pFontBase": "Suisse Int'l",
        "pFontWeight": 400,
        "pFontSize": 16,
        "pLineHeight": "120%",
        "pLetterSpacing": "-0.5%",
        "pParagraphSpacing": 10,
        "pIndent": 0,
        "pFontVariantNumeric": "String value",
        "pFontFeatureSettings": "String value",
        "bodyBookFontBase": "Suisse Int'l",
        "bodyBookFontWeight": 450,
        "bodyBookFontSize": 14,
        "bodyBookLineHeight": "120%",
        "bodyBookLetterSpacing": "-0.5%",
        "bodyBookParagraphSpacing": 10,
        "bodyBookIndent": 32,
        "bodyBookFontVariantNumeric": "String value",
        "bodyBookFontFeatureSettings": "String value",
        "bodyMediumFontBase": "Suisse Int'l",
        "bodyMediumFontWeight": 500,
        "bodyMediumFontSize": 14,
        "bodyMediumLineHeight": "120%",
        "bodyMediumLetterSpacing": "-0.5%",
        "bodyMediumParagraphSpacing": 10,
        "bodyMediumIndent": 32,
        "bodyMediumFontVariantNumeric": "String value",
        "bodyMediumFontFeatureSettings": "String value",
        "bodyRegularFontBase": "Suisse Int'l",
        "bodyRegularFontWeight": 400,
        "bodyRegularFontSize": 14,
        "bodyRegularLineHeight": "120%",
        "bodyRegularLetterSpacing": "-0.5%",
        "bodyRegularParagraphSpacing": 10,
        "bodyRegularIndent": 32,
        "bodyRegularFontVariantNumeric": "String value",
        "bodyRegularFontFeatureSettings": "String value",
        "bodyLightFontBase": "Suisse Int'l",
        "bodyLightFontWeight": 300,
        "bodyLightFontSize": 14,
        "bodyLightLineHeight": "120%",
        "bodyLightLetterSpacing": "-0.5%",
        "bodyLightParagraphSpacing": 10,
        "bodyLightIndent": 32,
        "bodyLightFontVariantNumeric": "String value",
        "bodyLightFontFeatureSettings": "String value"
    },
    "tablet": {
        "headingH1FontWeight": 300,
        "headingH1FontSize": 32,
        "headingH1ParagraphSpacing": 24,
        "headingH1Indent": 0,
        "headingH1FontVariantNumeric": "String value",
        "headingH1FontFeatureSettings": "String value",
        "headingH1LineHeight": "120%",
        "headingH1LetterSpacing": "-0.5%",
        "headingH1FontBase": "Suisse Int'l",
        "headingH2FontBase": "Suisse Int'l",
        "headingH2FontWeight": 300,
        "headingH2FontSize": 30,
        "headingH2LineHeight": "120%",
        "headingH2LetterSpacing": "-0.5%",
        "headingH2ParagraphSpacing": 24,
        "headingH2Indent": 0,
        "headingH2FontVariantNumeric": "String value",
        "headingH2FontFeatureSettings": "String value",
        "headingH3FontBase": "Suisse Int'l",
        "headingH3FontWeight": 400,
        "headingH3FontSize": 24,
        "headingH3LineHeight": "120%",
        "headingH3LetterSpacing": "-0.5%",
        "headingH3ParagraphSpacing": 24,
        "headingH3Indent": 0,
        "headingH3FontVariantNumeric": "String value",
        "headingH3FontFeatureSettings": "String value",
        "headingH4FontBase": "Suisse Int'l",
        "headingH4FontWeight": 450,
        "headingH4FontSize": 20,
        "headingH4LineHeight": "120%",
        "headingH4LetterSpacing": "-0.5%",
        "headingH4ParagraphSpacing": 10,
        "headingH4Indent": 0,
        "headingH4FontVariantNumeric": "String value",
        "headingH4FontFeatureSettings": "String value",
        "leadFontBase": "Suisse Int'l",
        "leadFontWeight": 400,
        "leadFontSize": 24,
        "leadLineHeight": "120%",
        "leadLetterSpacing": "-0.5%",
        "leadParagraphSpacing": 10,
        "leadIndent": 32,
        "leadFontVariantNumeric": "String value",
        "leadFontFeatureSettings": "String value",
        "largeFontBase": "Suisse Int'l",
        "largeFontWeight": 400,
        "largeFontSize": 18,
        "largeLineHeight": "120%",
        "largeLetterSpacing": "-0.5%",
        "largeParagraphSpacing": 10,
        "largeIndent": 0,
        "largeFontVariantNumeric": "String value",
        "largeFontFeatureSettings": "String value",
        "pFontBase": "Suisse Int'l",
        "pFontWeight": 400,
        "pFontSize": 16,
        "pLineHeight": "120%",
        "pLetterSpacing": "-0.5%",
        "pParagraphSpacing": 10,
        "pIndent": 0,
        "pFontVariantNumeric": "String value",
        "pFontFeatureSettings": "String value",
        "bodyBookFontBase": "Suisse Int'l",
        "bodyBookFontWeight": 450,
        "bodyBookFontSize": 14,
        "bodyBookLineHeight": "120%",
        "bodyBookLetterSpacing": "-0.5%",
        "bodyBookParagraphSpacing": 10,
        "bodyBookIndent": 32,
        "bodyBookFontVariantNumeric": "String value",
        "bodyBookFontFeatureSettings": "String value",
        "bodyMediumFontBase": "Suisse Int'l",
        "bodyMediumFontWeight": 500,
        "bodyMediumFontSize": 14,
        "bodyMediumLineHeight": "120%",
        "bodyMediumLetterSpacing": "-0.5%",
        "bodyMediumParagraphSpacing": 10,
        "bodyMediumIndent": 32,
        "bodyMediumFontVariantNumeric": "String value",
        "bodyMediumFontFeatureSettings": "String value",
        "bodyRegularFontBase": "Suisse Int'l",
        "bodyRegularFontWeight": 400,
        "bodyRegularFontSize": 14,
        "bodyRegularLineHeight": "120%",
        "bodyRegularLetterSpacing": "-0.5%",
        "bodyRegularParagraphSpacing": 10,
        "bodyRegularIndent": 32,
        "bodyRegularFontVariantNumeric": "String value",
        "bodyRegularFontFeatureSettings": "String value",
        "bodyLightFontBase": "Suisse Int'l",
        "bodyLightFontWeight": 300,
        "bodyLightFontSize": 14,
        "bodyLightLineHeight": "120%",
        "bodyLightLetterSpacing": "-0.5%",
        "bodyLightParagraphSpacing": 10,
        "bodyLightIndent": 32,
        "bodyLightFontVariantNumeric": "String value",
        "bodyLightFontFeatureSettings": "String value"
    },
    "desktopDefault": {
        "headingH1FontWeight": 300,
        "headingH1FontSize": 48,
        "headingH1ParagraphSpacing": 24,
        "headingH1Indent": 0,
        "headingH1FontVariantNumeric": "String value",
        "headingH1FontFeatureSettings": "String value",
        "headingH1LineHeight": "120%",
        "headingH1LetterSpacing": "-0.5%",
        "headingH1FontBase": "Suisse Int'l",
        "headingH2FontBase": "Suisse Int'l",
        "headingH2FontWeight": 300,
        "headingH2FontSize": 36,
        "headingH2LineHeight": "120%",
        "headingH2LetterSpacing": "-0.5%",
        "headingH2ParagraphSpacing": 24,
        "headingH2Indent": 0,
        "headingH2FontVariantNumeric": "String value",
        "headingH2FontFeatureSettings": "String value",
        "headingH3FontBase": "Suisse Int'l",
        "headingH3FontWeight": 400,
        "headingH3FontSize": 32,
        "headingH3LineHeight": "120%",
        "headingH3LetterSpacing": "-0.5%",
        "headingH3ParagraphSpacing": 24,
        "headingH3Indent": 0,
        "headingH3FontVariantNumeric": "String value",
        "headingH3FontFeatureSettings": "String value",
        "headingH4FontBase": "Suisse Int'l",
        "headingH4FontWeight": 450,
        "headingH4FontSize": 24,
        "headingH4LineHeight": "120%",
        "headingH4LetterSpacing": "-0.5%",
        "headingH4ParagraphSpacing": 10,
        "headingH4Indent": 0,
        "headingH4FontVariantNumeric": "String value",
        "headingH4FontFeatureSettings": "String value",
        "leadFontBase": "Suisse Int'l",
        "leadFontWeight": 400,
        "leadFontSize": 24,
        "leadLineHeight": "120%",
        "leadLetterSpacing": "-0.5%",
        "leadParagraphSpacing": 10,
        "leadIndent": 32,
        "leadFontVariantNumeric": "String value",
        "leadFontFeatureSettings": "String value",
        "largeFontBase": "Suisse Int'l",
        "largeFontWeight": 400,
        "largeFontSize": 18,
        "largeLineHeight": "120%",
        "largeLetterSpacing": "-0.5%",
        "largeParagraphSpacing": 10,
        "largeIndent": 0,
        "largeFontVariantNumeric": "String value",
        "largeFontFeatureSettings": "String value",
        "pFontBase": "Suisse Int'l",
        "pFontWeight": 400,
        "pFontSize": 16,
        "pLineHeight": "120%",
        "pLetterSpacing": "-0.5%",
        "pParagraphSpacing": 10,
        "pIndent": 0,
        "pFontVariantNumeric": "String value",
        "pFontFeatureSettings": "String value",
        "bodyBookFontBase": "Suisse Int'l",
        "bodyBookFontWeight": 450,
        "bodyBookFontSize": 14,
        "bodyBookLineHeight": "120%",
        "bodyBookLetterSpacing": "-0.5%",
        "bodyBookParagraphSpacing": 10,
        "bodyBookIndent": 32,
        "bodyBookFontVariantNumeric": "String value",
        "bodyBookFontFeatureSettings": "String value",
        "bodyMediumFontBase": "Suisse Int'l",
        "bodyMediumFontWeight": 500,
        "bodyMediumFontSize": 14,
        "bodyMediumLineHeight": "120%",
        "bodyMediumLetterSpacing": "-0.5%",
        "bodyMediumParagraphSpacing": 10,
        "bodyMediumIndent": 32,
        "bodyMediumFontVariantNumeric": "String value",
        "bodyMediumFontFeatureSettings": "String value",
        "bodyRegularFontBase": "Suisse Int'l",
        "bodyRegularFontWeight": 400,
        "bodyRegularFontSize": 14,
        "bodyRegularLineHeight": "120%",
        "bodyRegularLetterSpacing": "-0.5%",
        "bodyRegularParagraphSpacing": 10,
        "bodyRegularIndent": 32,
        "bodyRegularFontVariantNumeric": "String value",
        "bodyRegularFontFeatureSettings": "String value",
        "bodyLightFontBase": "Suisse Int'l",
        "bodyLightFontWeight": 300,
        "bodyLightFontSize": 14,
        "bodyLightLineHeight": "120%",
        "bodyLightLetterSpacing": "-0.5%",
        "bodyLightParagraphSpacing": 10,
        "bodyLightIndent": 32,
        "bodyLightFontVariantNumeric": "String value",
        "bodyLightFontFeatureSettings": "String value"
    },
    "bigDesktop": {
        "headingH1FontWeight": 300,
        "headingH1FontSize": 60,
        "headingH1ParagraphSpacing": 24,
        "headingH1Indent": 0,
        "headingH1FontVariantNumeric": "String value",
        "headingH1FontFeatureSettings": "String value",
        "headingH1LineHeight": "120%",
        "headingH1LetterSpacing": "-0.5%",
        "headingH1FontBase": "Suisse Int'l",
        "headingH2FontBase": "Suisse Int'l",
        "headingH2FontWeight": 300,
        "headingH2FontSize": 48,
        "headingH2LineHeight": "120%",
        "headingH2LetterSpacing": "-0.5%",
        "headingH2ParagraphSpacing": 24,
        "headingH2Indent": 0,
        "headingH2FontVariantNumeric": "String value",
        "headingH2FontFeatureSettings": "String value",
        "headingH3FontBase": "Suisse Int'l",
        "headingH3FontWeight": 400,
        "headingH3FontSize": 36,
        "headingH3LineHeight": "120%",
        "headingH3LetterSpacing": "-0.5%",
        "headingH3ParagraphSpacing": 24,
        "headingH3Indent": 0,
        "headingH3FontVariantNumeric": "String value",
        "headingH3FontFeatureSettings": "String value",
        "headingH4FontBase": "Suisse Int'l",
        "headingH4FontWeight": 450,
        "headingH4FontSize": 30,
        "headingH4LineHeight": "120%",
        "headingH4LetterSpacing": "-0.5%",
        "headingH4ParagraphSpacing": 10,
        "headingH4Indent": 0,
        "headingH4FontVariantNumeric": "String value",
        "headingH4FontFeatureSettings": "String value",
        "leadFontBase": "Suisse Int'l",
        "leadFontWeight": 400,
        "leadFontSize": 24,
        "leadLineHeight": "120%",
        "leadLetterSpacing": "-0.5%",
        "leadParagraphSpacing": 10,
        "leadIndent": 32,
        "leadFontVariantNumeric": "String value",
        "leadFontFeatureSettings": "String value",
        "largeFontBase": "Suisse Int'l",
        "largeFontWeight": 400,
        "largeFontSize": 18,
        "largeLineHeight": "120%",
        "largeLetterSpacing": "-0.5%",
        "largeParagraphSpacing": 10,
        "largeIndent": 0,
        "largeFontVariantNumeric": "String value",
        "largeFontFeatureSettings": "String value",
        "pFontBase": "Suisse Int'l",
        "pFontWeight": 400,
        "pFontSize": 16,
        "pLineHeight": "120%",
        "pLetterSpacing": "-0.5%",
        "pParagraphSpacing": 10,
        "pIndent": 0,
        "pFontVariantNumeric": "String value",
        "pFontFeatureSettings": "String value",
        "bodyBookFontBase": "Suisse Int'l",
        "bodyBookFontWeight": 450,
        "bodyBookFontSize": 14,
        "bodyBookLineHeight": "120%",
        "bodyBookLetterSpacing": "-0.5%",
        "bodyBookParagraphSpacing": 10,
        "bodyBookIndent": 32,
        "bodyBookFontVariantNumeric": "String value",
        "bodyBookFontFeatureSettings": "String value",
        "bodyMediumFontBase": "Suisse Int'l",
        "bodyMediumFontWeight": 500,
        "bodyMediumFontSize": 14,
        "bodyMediumLineHeight": "120%",
        "bodyMediumLetterSpacing": "-0.5%",
        "bodyMediumParagraphSpacing": 10,
        "bodyMediumIndent": 32,
        "bodyMediumFontVariantNumeric": "String value",
        "bodyMediumFontFeatureSettings": "String value",
        "bodyRegularFontBase": "Suisse Int'l",
        "bodyRegularFontWeight": 400,
        "bodyRegularFontSize": 14,
        "bodyRegularLineHeight": "120%",
        "bodyRegularLetterSpacing": "-0.5%",
        "bodyRegularParagraphSpacing": 10,
        "bodyRegularIndent": 32,
        "bodyRegularFontVariantNumeric": "String value",
        "bodyRegularFontFeatureSettings": "String value",
        "bodyLightFontBase": "Suisse Int'l",
        "bodyLightFontWeight": 300,
        "bodyLightFontSize": 14,
        "bodyLightLineHeight": "120%",
        "bodyLightLetterSpacing": "-0.5%",
        "bodyLightParagraphSpacing": 10,
        "bodyLightIndent": 32,
        "bodyLightFontVariantNumeric": "String value",
        "bodyLightFontFeatureSettings": "String value"
    }
}